builder_python/__init__.py
builder_python/builder.py
builder_python/py.typed
builder_python/template.tar
skelly/__init__.py
skelly/args.py
skelly/main.py
skelly/py.typed
skelly/builder/__init__.py
skelly/builder/builder.py
skelly/builder/console/__init__.py
skelly/builder/console/git.py
skelly/builder/python/__init__.py
skelly/builder/python/venv.py
skelly-0.0.6.dist-info/LICENSE
skelly-0.0.6.dist-info/METADATA
skelly-0.0.6.dist-info/WHEEL
skelly-0.0.6.dist-info/entry_points.txt
skelly-0.0.6.dist-info/top_level.txt
skelly-0.0.6.dist-info/RECORD
