Metadata-Version: 2.1
Name: skelly
Version: 0.0.6
Summary: Generate a project skeleton
Home-page: https://gitlab.com/narvin/skelly
Author-email: Narvin Singh <Narvin.A.Singh@gmail.com>
License: The MIT License (MIT)
Project-URL: Homepage, https://gitlab.com/narvin/skelly
Project-URL: Repository, https://gitlab.com/narvin/skelly
Project-URL: Bug Tracker, https://gitlab.com/narvin/skelly/-/issues
Keywords: code generator,skeleton,stub,template
Platform: UNKNOWN
Classifier: Programming Language :: Python :: 3
Classifier: License :: OSI Approved :: MIT License
Classifier: Operating System :: OS Independent
Requires-Python: >=3.7
License-File: LICENSE
Requires-Dist: importlib-metadata ; python_version < "3.8"
